uva/__init__.py
uva/__main__.py
uva/commands/__init__.py
uva/commands/commands.py
uva/helpers/__init__.py
uva/helpers/helpers.py
uva/localdb/__init__.py
uva/localdb/localdb.py
uva/main.py
uva-0.4.0.dist-info/METADATA
uva-0.4.0.dist-info/WHEEL
uva-0.4.0.dist-info/entry_points.txt
uva-0.4.0.dist-info/RECORD
