Metadata-Version: 2.1
Name: uva
Version: 0.4.0
Summary: 
Author: Aleksandar Markovic
Author-email: aleksamarkoni@gmail.com
Requires-Python: >=3.10,<4.0
Classifier: Programming Language :: Python :: 3
Classifier: Programming Language :: Python :: 3.10
Classifier: Programming Language :: Python :: 3.11
Requires-Dist: bs4 (>=0.0.1,<0.0.2)
Requires-Dist: html5lib (>=1.1,<2.0)
Requires-Dist: pickledb (>=0.9.2,<0.10.0)
Requires-Dist: requests (>=2.28.1,<3.0.0)
Requires-Dist: timeago (>=1.0.16,<2.0.0)
Requires-Dist: typer[all] (>=0.7.0,<0.8.0)
